shredy_git/__init__.py
shredy_git/shredy_git.py
shredy-1.0.1.dist-info/METADATA
shredy-1.0.1.dist-info/WHEEL
shredy-1.0.1.dist-info/entry_points.txt
shredy-1.0.1.dist-info/top_level.txt
shredy-1.0.1.dist-info/RECORD
