Metadata-Version: 2.1
Name: shredy
Version: 1.0.1
Summary: Create support docs for SR&ED reporting
Home-page: https://github.com/csshirri/shredy_git.git
Author: Cody Shirriff
Author-email: shredy.tax@gmail.com
Classifier: Programming Language :: Python :: 3
Classifier: License :: OSI Approved :: MIT License
Classifier: Operating System :: OS Independent
Requires-Python: >=3.6
Requires-Dist: certifi==2024.12.14
Requires-Dist: charset-normalizer==3.4.0
Requires-Dist: contourpy==1.3.0
Requires-Dist: cycler==0.12.1
Requires-Dist: fonttools==4.55.3
Requires-Dist: fpdf2==2.8.2
Requires-Dist: idna==3.10
Requires-Dist: kiwisolver==1.4.7
Requires-Dist: matplotlib==3.10.0
Requires-Dist: numpy==2.2.0
Requires-Dist: packaging==24.2
Requires-Dist: pandas==2.2.3
Requires-Dist: pillow==11.0.0
Requires-Dist: pyparsing==3.2.0
Requires-Dist: python-dateutil==2.9.0.post0
Requires-Dist: pytz==2024.2
Requires-Dist: requests==2.32.3
Requires-Dist: seaborn==0.13.2
Requires-Dist: six==1.17.0
Requires-Dist: tzdata==2024.2
Requires-Dist: urllib3==2.2.3
